python_dynamodb_lock/__init__.py
python_dynamodb_lock/python_dynamodb_lock.py
python_dynamodb_lock_whatnick-0.9.3.dist-info/AUTHORS.rst
python_dynamodb_lock_whatnick-0.9.3.dist-info/LICENSE
python_dynamodb_lock_whatnick-0.9.3.dist-info/METADATA
python_dynamodb_lock_whatnick-0.9.3.dist-info/WHEEL
python_dynamodb_lock_whatnick-0.9.3.dist-info/top_level.txt
python_dynamodb_lock_whatnick-0.9.3.dist-info/RECORD
