Metadata-Version: 2.1
Name: python-dynamodb-lock-whatnick
Version: 0.9.3
Summary: Python library that emulates the java-based dynamo-db-client from awslabs
Home-page: https://github.com/whatnick/python_dynamodb_lock
Author: Mohan Kishore
Author-email: mohankishore@yahoo.com
License: Apache Software License 2.0
Keywords: python_dynamodb_lock
Platform: UNKNOWN
Classifier: Development Status :: 4 - Beta
Classifier: Intended Audience :: Developers
Classifier: License :: OSI Approved :: Apache Software License
Classifier: Natural Language :: English
Classifier: Programming Language :: Python :: 3
Classifier: Programming Language :: Python :: 3.6
Classifier: Programming Language :: Python :: 3.7
Requires-Dist: boto3
Requires-Dist: botocore
